random_forestry/__init__.py
random_forestry/extension.cpython-39-darwin.so
random_forestry/forestry.py
random_forestry/preprocessing.py
random_forestry/processed_dta.py
random_forestry/test.py
random_forestry/validators/__init__.py
random_forestry/validators/base_validator.py
random_forestry/validators/fit_validator.py
random_forestry/validators/predict_validator.py
random_forestry-0.10.0.dist-info/LICENSE
random_forestry-0.10.0.dist-info/METADATA
random_forestry-0.10.0.dist-info/WHEEL
random_forestry-0.10.0.dist-info/top_level.txt
random_forestry-0.10.0.dist-info/RECORD
