Metadata-Version: 2.1
Name: random-forestry
Version: 0.10.0
Summary: Random forest estimator
License: The MIT License (MIT)
Project-URL: Homepage, https://github.com/forestry-labs/Rforestry#readme
Classifier: License :: OSI Approved :: MIT License
Classifier: Programming Language :: Python
Classifier: Programming Language :: Python :: 3
Requires-Python: >=3.8
License-File: LICENSE
Requires-Dist: numpy (<2,>=1.23.5)
Requires-Dist: pandas (<1.5,>=1.4)
Requires-Dist: statsmodels (<1,>=0.13.5)
Requires-Dist: pydantic (<2,>=1.10.6)
Requires-Dist: scikit-learn (<2,==1.2.2)
Requires-Dist: typing-extensions ; python_version < "3.11"
Provides-Extra: dev
Requires-Dist: bumpver (>=2022.1120) ; extra == 'dev'
Requires-Dist: pip-tools (>=6.12.3) ; extra == 'dev'
Provides-Extra: test
Requires-Dist: pytest (>=7.2.2) ; extra == 'test'
